main.py
setup.py
keras_preprocess.egg-info/PKG-INFO
keras_preprocess.egg-info/SOURCES.txt
keras_preprocess.egg-info/dependency_links.txt
keras_preprocess.egg-info/requires.txt
keras_preprocess.egg-info/top_level.txt